pyigtl/__init__.py
pyigtl/_version.py
pyigtl/comm.py
pyigtl/messages.py
pyigtl/tests/__init__.py
pyigtl/tests/test_basic_comm.py
pyigtl-0.3.1.dist-info/LICENSE
pyigtl-0.3.1.dist-info/METADATA
pyigtl-0.3.1.dist-info/WHEEL
pyigtl-0.3.1.dist-info/top_level.txt
pyigtl-0.3.1.dist-info/RECORD
