Metadata-Version: 2.1
Name: pyigtl
Version: 0.3.1
Summary: Python interface for OpenIGTLink
Home-page: https://github.com/lassoan/pyigtl
Download-URL: https://github.com/lassoan/pyigtl/archive/master.zip
Author: Andras Lasso, Daniel Hoyer Iversen, Kyle Sunderland
Author-email: lasso@queensu.ca
Maintainer: Andras Lasso
Maintainer-email: lasso@queensu.ca
Keywords: openigtlink igt medical imaging
Classifier: License :: OSI Approved :: MIT License
Classifier: Intended Audience :: Developers
Classifier: Intended Audience :: Healthcare Industry
Classifier: Intended Audience :: Science/Research
Classifier: Development Status :: 4 - Beta
Classifier: Programming Language :: Python :: 3
Classifier: Operating System :: OS Independent
Classifier: Topic :: Scientific/Engineering :: Medical Science Apps.
Classifier: Topic :: System :: Networking
Requires-Python: >=3.6
License-File: LICENSE
Requires-Dist: crcmod
Requires-Dist: numpy
